{"lastUsed":1660874406772,"path":"D:\/SSAFY\/workspace\/algorithm","projectCount":3,"recentFiles":[{"path":"\/SWEA\/src\/test","parentWorkspace":"D:\/Study\/workspace\/algorithm","name":"Solution_5644_무선충전.java","lastModified":1660834195036,"locationURI":"file:\/D:\/Study\/workspace\/algorithm\/SWEA\/src\/test\/Solution_5644_무선충전.java"},{"path":"\/SWEA\/src\/test","parentWorkspace":"D:\/Study\/workspace\/algorithm","name":"Solution_4012_요리사.java","lastModified":1660834195036,"locationURI":"file:\/D:\/Study\/workspace\/algorithm\/SWEA\/src\/test\/Solution_4012_요리사.java"},{"path":"\/BOJ\/src\/baekjoon","parentWorkspace":"D:\/SSAFY\/workspace\/algorithm","name":"Main_1260_DFS와BFS.java","lastModified":1660871569314,"locationURI":"file:\/D:\/SSAFY\/workspace\/algorithm\/BOJ\/src\/baekjoon\/Main_1260_DFS와BFS.java"},{"path":"\/SWEA\/src\/d2","parentWorkspace":"D:\/Study\/workspace\/algorithm","name":"Solution_1954_달팽이숫자.java","lastModified":1660834150885,"locationURI":"file:\/D:\/Study\/workspace\/algorithm\/SWEA\/src\/d2\/Solution_1954_달팽이숫자.java"},{"path":"\/SWEA\/src\/d5","parentWorkspace":"D:\/SSAFY\/workspace\/algorithm","name":"Solution_1247_최적경로.java","lastModified":1660874406888,"locationURI":"file:\/D:\/SSAFY\/workspace\/algorithm\/SWEA\/src\/d5\/Solution_1247_최적경로.java"},{"path":"\/Jungol\/src","parentWorkspace":"D:\/Study\/workspace\/algorithm","name":"Main_1828_냉장고.java","lastModified":1660834124316,"locationURI":"file:\/D:\/Study\/workspace\/algorithm\/Jungol\/src\/Main_1828_냉장고.java"}]}